qtvoila/__init__.py
qtvoila/qtvoila.py
qtvoila-2.1.0.dist-info/LICENSE
qtvoila-2.1.0.dist-info/METADATA
qtvoila-2.1.0.dist-info/WHEEL
qtvoila-2.1.0.dist-info/top_level.txt
qtvoila-2.1.0.dist-info/RECORD
