Metadata-Version: 2.1
Name: qtvoila
Version: 2.1.0
Summary: A Qt for Python extension for Voila
Home-page: https://github.com/luiztauffer/qtvoila
Author: Luiz Tauffer
Author-email: luiz@taufferconsulting.com
License: BSD license
Keywords: qtvoila
Classifier: Intended Audience :: Developers
Classifier: License :: OSI Approved :: BSD License
Classifier: Natural Language :: English
Classifier: Programming Language :: Python :: 3.7
Classifier: Programming Language :: Python :: 3.8
Requires-Python: >=3.5
License-File: LICENSE
Requires-Dist: PySide6
Requires-Dist: voila
Requires-Dist: numpy
Requires-Dist: psutil
